dynaml_lib/__init__.py
dynaml_lib/experiment.py
dynaml_lib-0.0.1.dist-info/LICENSE
dynaml_lib-0.0.1.dist-info/METADATA
dynaml_lib-0.0.1.dist-info/WHEEL
dynaml_lib-0.0.1.dist-info/top_level.txt
dynaml_lib-0.0.1.dist-info/RECORD
